LICENSE.txt
MANIFEST.in
README.rst
graphyte.py
setup.py
test_graphyte.py
graphyte.egg-info/PKG-INFO
graphyte.egg-info/SOURCES.txt
graphyte.egg-info/dependency_links.txt
graphyte.egg-info/top_level.txt